jni-1.2.0b1.dist-info/METADATA
jni-1.2.0b1.dist-info/RECORD
jni-1.2.0b1.dist-info/WHEEL
jni-1.2.0b1.dist-info/licenses/LICENSE
jni-1.2.0b1.dist-info/top_level.txt
jni/capi/jni.cp311-win_amd64.pyd
jni/cython/jni.cp311-win_amd64.pyd
jni/jni.c
jni/jni.cfg
jni/pvm.c
jni\__about__.pyc
jni\__config__.pyc
jni\__init__.pyc
jni\_config.pyc
jni\_util.pyc
jni\capi\__init__.pyc
jni\cffi\__init__.pyc
jni\cffi\jni.pyc
jni\ctypes\__init__.pyc
jni\ctypes\_ct.pyc
jni\cython\__init__.pyc
