Metadata-Version: 2.4
Name: jni
Version: 1.2.0b1
Summary: Python bridge for the Java Native Interface.
Author: Adam Karpierz
Author-email: adam@karpierz.net
Maintainer: Adam Karpierz
Maintainer-email: adam@karpierz.net
License-Expression: CC-BY-NC-ND-4.0 OR LicenseRef-Proprietary
Project-URL: Homepage, https://pypi.org/project/jni/
Project-URL: Documentation, https://jni.readthedocs.io/
Project-URL: Download, https://pypi.org/project/jni/
Project-URL: Source, https://github.com/karpierz/jni
Project-URL: Issues, https://github.com/karpierz/jni/issues
Keywords: jni,jvm,jtypes,jt,jpype,jep,pyjnius,jpy,javabridge,pyjava,jcc,py4j,jython,java,pythonjava,rubicon-java
Platform: any
Classifier: Development Status :: 4 - Beta
Classifier: Intended Audience :: Developers
Classifier: Operating System :: OS Independent
Classifier: Natural Language :: Polish
Classifier: Programming Language :: Python
Classifier: Programming Language :: Python :: 3
Classifier: Programming Language :: Python :: 3.10
Classifier: Programming Language :: Python :: 3.11
Classifier: Programming Language :: Python :: 3.12
Classifier: Programming Language :: Python :: 3.13
Classifier: Programming Language :: Python :: 3.14
Classifier: Programming Language :: Python :: 3 :: Only
Classifier: Programming Language :: Python :: Implementation :: CPython
Classifier: Programming Language :: Python :: Implementation :: PyPy
Classifier: Programming Language :: Java
Classifier: Programming Language :: C
Classifier: Topic :: Software Development :: Libraries :: Python Modules
Classifier: Topic :: Software Development :: Libraries :: Java Libraries
Requires-Python: <4.0.0,>=3.10.0
License-File: LICENSE
Requires-Dist: setuptools>=80.9.0
Requires-Dist: pkg-about>=1.3.6
Provides-Extra: cffi
Requires-Dist: cffi>=1.17.1; extra == "cffi"
Provides-Extra: cython
Requires-Dist: cython>=3.1.2; extra == "cython"
Provides-Extra: doc
Requires-Dist: Sphinx>=8.1.3; extra == "doc"
Requires-Dist: sphinx-autodoc-typehints>=3.0.1; extra == "doc"
Requires-Dist: sphinx-toolbox>=4.0.0; extra == "doc"
Requires-Dist: sphinx-tabs>=3.4.5; extra == "doc"
Requires-Dist: sphinx-copybutton>=0.5.2; extra == "doc"
Requires-Dist: sphinxcontrib-spelling>=8.0.1; extra == "doc"
Requires-Dist: sphinx-lint>=1.0.0; extra == "doc"
Requires-Dist: restructuredtext-lint>=1.4.0; extra == "doc"
Requires-Dist: nbsphinx>=0.9.7; extra == "doc"
Provides-Extra: test
Requires-Dist: deepdiff>=8.5.0; extra == "test"
Requires-Dist: rich>=14.0.0; extra == "test"
Dynamic: license-file
